GFHunter/__init__.py
GFHunter/crossing_reference_based_refinement.py
GFHunter/main.py
GFHunter/preprocessing.py
GFHunter/sc_handle.py
GFHunter/transcriptome_based_detection.py
GFHunter-1.0.1.dist-info/METADATA
GFHunter-1.0.1.dist-info/WHEEL
GFHunter-1.0.1.dist-info/entry_points.txt
GFHunter-1.0.1.dist-info/top_level.txt
GFHunter-1.0.1.dist-info/RECORD
